django_we/__init__.py
django_we/admin.py
django_we/decorators.py
django_we/models.py
django_we/urls.py
django_we/views.py
django_we/migrations/0001_initial.py
django_we/migrations/0002_componentverifyticketloginfo.py
django_we/migrations/0003_subscribeuserinfo.py
django_we/migrations/0004_auto_20190820_1220.py
django_we/migrations/0005_auto_20201130_0131.py
django_we/migrations/__init__.py
django_we/templates/django_we/errmsg.html
django_we-1.5.9.dist-info/METADATA
django_we-1.5.9.dist-info/WHEEL
django_we-1.5.9.dist-info/top_level.txt
django_we-1.5.9.dist-info/RECORD
