Metadata-Version: 2.1
Name: django-we
Version: 1.5.9
Summary: Django WeChat OAuth2/Share/Token API
Home-page: https://github.com/django-xxx/django-we
Author: Hackathon
Author-email: kimi.huang@brightcells.com
Keywords: django-we
Classifier: Development Status :: 5 - Production/Stable
Classifier: Environment :: Web Environment
Classifier: Framework :: Django
Classifier: Intended Audience :: Developers
Classifier: Programming Language :: Python
Classifier: Topic :: Software Development :: Libraries :: Python Modules
Classifier: Topic :: Office/Business :: Financial :: Spreadsheet
Requires-Dist: django-admin (>=1.2.4)
Requires-Dist: django-detect
Requires-Dist: django-json-response
Requires-Dist: django-logit
Requires-Dist: django-models-ext (>=1.1.10)
Requires-Dist: django-six
Requires-Dist: furl
Requires-Dist: jsonfield
Requires-Dist: pywe-component-authorizer-token (>=1.1.1)
Requires-Dist: pywe-component-ticket
Requires-Dist: pywe-decrypt (>=1.1.3)
Requires-Dist: pywe-jssdk (>=1.1.0)
Requires-Dist: pywe-oauth (>=1.0.5)
Requires-Dist: pywe-qrcode
Requires-Dist: pywe-sign (>=1.0.7)
Requires-Dist: pywe-storage
Requires-Dist: pywe-token (>=1.2.1)
Requires-Dist: pywe-xml
